dekgen-0.1.43.dist-info/METADATA
dekgen-0.1.43.dist-info/WHEEL
dekgen-0.1.43.dist-info/entry_points.txt
dekgen/__init__.py
dekgen/click/__entry__.py
dekgen/click/__init__.py
dekgen/code/__init__.py
dekgen/code/python/__init__.py
dekgen/code/python/generator.py
dekgen/code/python/imports.py
dekgen/code/python/template/__init__.py
dekgen/code/python/template/env.py
dekgen/resloader/__init__.py
dekgen/tmpl/__init__.py
dekgen/tmpl/env.py
dekgen/tmpl/exceptions.py
dekgen/tmpl/generator.py
dekgen/tmpl/part.py
dekgen/tmpl/render.py
dekgen/tmpl/template.py
dekgen/utils/__init__.py
dekgen/utils/yaml/__init__.py
dekgen/utils/yaml/tags/__init__.py
dekgen/utils/yaml/tags/tmpl.py
dekgen-0.1.43.dist-info/RECORD
