Metadata-Version: 2.1
Name: dekgen
Version: 0.1.43
Author-Email: sanzenwin <sanzenwin@gmail.com>
License: MIT
Requires-Python: >=3.7
Requires-Dist: jinja2<=3.1.2
Requires-Dist: dektools[date,ignore,yaml]<1.0.0
Provides-Extra: code-py
Requires-Dist: black<=23.1.0; extra == "code-py"
